LICENSE.txt
MANIFEST.in
README
VERSION
VERSION.orig
contributors.txt
requirements.txt
setup.cfg
setup.py
nekbot/__init__.py
nekbot.protocols.telegram.egg-info/PKG-INFO
nekbot.protocols.telegram.egg-info/SOURCES.txt
nekbot.protocols.telegram.egg-info/dependency_links.txt
nekbot.protocols.telegram.egg-info/entry_points.txt
nekbot.protocols.telegram.egg-info/namespace_packages.txt
nekbot.protocols.telegram.egg-info/not-zip-safe
nekbot.protocols.telegram.egg-info/requires.txt
nekbot.protocols.telegram.egg-info/top_level.txt
nekbot/protocols/__init__.py
nekbot/protocols/telegram/__init__.py
nekbot/protocols/telegram/global_settings.py
nekbot/protocols/telegram/group_chat.py
nekbot/protocols/telegram/message.py
nekbot/protocols/telegram/message.py.orig
nekbot/protocols/telegram/user.py
nekbot/protocols/telegram/bin/generate
nekbot/protocols/telegram/bin/telegram-cli
nekbot/protocols/telegram/bin/tg-server.pub
nekbot/protocols/telegram/bin/tl-parser