Metadata-Version: 1.1
Name: nekbot.protocols.telegram
Version: 0.1.0.16
Summary: Telegram Protocol for Nekbot, a modular multiprotocol bot.
Home-page: https://bitbucket.org/Nekmo/nekbot.protocols.telegram
Author: Nekmo
Author-email: contacto@nekmo.com
License: UNKNOWN
Download-URL: https://bitbucket.org/Nekmo/nekbot.protocols.telegram/get/default.tar.gz
Keywords: nekbot,bot,telegram,chat
Platform: linux
Classifier: Natural Language :: Spanish
Classifier: Development Status :: 1 - Planning
Classifier: License :: OSI Approved :: MIT License
Classifier: Intended Audience :: Developers
Classifier: Environment :: Console
Classifier: Topic :: Communications :: Chat
Classifier: Topic :: Communications :: Chat :: Internet Relay Chat
Classifier: Topic :: Communications :: Conferencing
Classifier: Operating System :: POSIX :: Linux
Classifier: Programming Language :: Python
Classifier: Programming Language :: Python :: 2
Classifier: Programming Language :: Python :: 2.6
Classifier: Programming Language :: Python :: 2.7
Classifier: Programming Language :: Python :: 3
Classifier: Programming Language :: Python :: 3.2
Classifier: Programming Language :: Python :: 3.3
Classifier: Programming Language :: Python :: 3.4
Provides: nekbot.protocols.telegram
